ipmi_monitor/__init__.py
ipmi_monitor/app.py
ipmi_monitor/cli.py
ipmi_monitor/quickstart.py
ipmi_monitor/reverse_proxy.py
ipmi_monitor/service.py
ipmi_monitor/wizard.py
ipmi_monitor/static/favicon.png
ipmi_monitor/templates/change_password.html
ipmi_monitor/templates/dashboard.html
ipmi_monitor/templates/docs.html
ipmi_monitor/templates/landing.html.j2
ipmi_monitor/templates/login.html
ipmi_monitor/templates/nginx.conf.j2
ipmi_monitor/templates/server_detail.html
ipmi_monitor/templates/settings.html
ipmi_monitor/templates/setup.html
ipmi_monitor-1.0.8.dist-info/METADATA
ipmi_monitor-1.0.8.dist-info/WHEEL
ipmi_monitor-1.0.8.dist-info/entry_points.txt
ipmi_monitor-1.0.8.dist-info/top_level.txt
ipmi_monitor-1.0.8.dist-info/RECORD
