Metadata-Version: 2.4
Name: ipmi-monitor
Version: 1.0.8
Summary: IPMI/BMC Server Monitoring with AI-Powered Insights
Author-email: CryptoLabs <info@cryptolabs.co.za>
License: MIT
Project-URL: Homepage, https://github.com/cryptolabsza/ipmi-monitor
Project-URL: Documentation, https://cryptolabsza.github.io/ipmi-monitor/
Project-URL: Repository, https://github.com/cryptolabsza/ipmi-monitor
Project-URL: Issues, https://github.com/cryptolabsza/ipmi-monitor/issues
Project-URL: Discord, https://discord.gg/7yeHdf5BuC
Keywords: ipmi,bmc,server,monitoring,gpu,datacenter,ai
Classifier: Development Status :: 4 - Beta
Classifier: Environment :: Console
Classifier: Environment :: Web Environment
Classifier: Framework :: Flask
Classifier: Intended Audience :: System Administrators
Classifier: License :: OSI Approved :: MIT License
Classifier: Operating System :: POSIX :: Linux
Classifier: Programming Language :: Python :: 3
Classifier: Programming Language :: Python :: 3.9
Classifier: Programming Language :: Python :: 3.10
Classifier: Programming Language :: Python :: 3.11
Classifier: Programming Language :: Python :: 3.12
Classifier: Topic :: System :: Monitoring
Classifier: Topic :: System :: Systems Administration
Requires-Python: >=3.9
Requires-Dist: flask>=3.0.0
Requires-Dist: flask-sqlalchemy>=3.1.1
Requires-Dist: gunicorn>=21.2.0
Requires-Dist: requests>=2.31.0
Requires-Dist: prometheus-client>=0.19.0
Requires-Dist: click>=8.1.0
Requires-Dist: rich>=13.0.0
Requires-Dist: questionary>=2.0.0
Requires-Dist: pyyaml>=6.0
Requires-Dist: paramiko>=3.0.0
Requires-Dist: jinja2>=3.0.0
Provides-Extra: dev
Requires-Dist: pytest>=7.0.0; extra == "dev"
Requires-Dist: pytest-cov>=4.0.0; extra == "dev"
Requires-Dist: black>=23.0.0; extra == "dev"
Requires-Dist: ruff>=0.1.0; extra == "dev"
